sum.py
topsis_K_Vinay_101803142-0.0.1.dist-info/LICENSE.txt
topsis_K_Vinay_101803142-0.0.1.dist-info/METADATA
topsis_K_Vinay_101803142-0.0.1.dist-info/WHEEL
topsis_K_Vinay_101803142-0.0.1.dist-info/top_level.txt
topsis_K_Vinay_101803142-0.0.1.dist-info/RECORD
